iaccess/__init__.py
iaccess/compiler.py
iaccess/connector.py
iaccess/dialect.py
iaccess/provision.py
iaccess/requirements.py
iaccess/information_schema/__init__.py
iaccess/information_schema/iseries.py
iaccess-0.6.0.dist-info/AUTHORS.rst
iaccess-0.6.0.dist-info/LICENSE
iaccess-0.6.0.dist-info/METADATA
iaccess-0.6.0.dist-info/WHEEL
iaccess-0.6.0.dist-info/entry_points.txt
iaccess-0.6.0.dist-info/top_level.txt
iaccess-0.6.0.dist-info/RECORD
