Metadata-Version: 2.1
Name: iaccess
Version: 0.6.0
Summary: Provides support for DB2 for iSeries for remote python clients using IBM i Access Client Solutions ODBC driver
Home-page: https://github.com/soundstripe/iaccess
Author: Steven Clayton James
Author-email: steven@waitforitjames.com
License: MIT license
Keywords: iaccess
Classifier: Development Status :: 2 - Pre-Alpha
Classifier: Intended Audience :: Developers
Classifier: License :: OSI Approved :: MIT License
Classifier: Natural Language :: English
Classifier: Programming Language :: Python :: 3
Classifier: Programming Language :: Python :: 3.6
Classifier: Programming Language :: Python :: 3.7
Classifier: Programming Language :: Python :: 3.8
Classifier: Topic :: Database
Requires-Python: >=3.6
License-File: LICENSE
License-File: AUTHORS.rst
Requires-Dist: sqlalchemy
Requires-Dist: pyodbc !=4.0.30
